umnet_nornir_plugins/__init__.py
umnet_nornir_plugins/connections.py
umnet_nornir_plugins/runners.py
umnet_nornir_plugins/tasks.py
umnet_nornir_plugins-0.1.1.dist-info/METADATA
umnet_nornir_plugins-0.1.1.dist-info/WHEEL
umnet_nornir_plugins-0.1.1.dist-info/entry_points.txt
umnet_nornir_plugins-0.1.1.dist-info/RECORD
