Metadata-Version: 2.3
Name: umnet-nornir-plugins
Version: 0.1.1
Summary: Nornir plugins for UMnet
Author: Amy Liebowitz
Author-email: amylieb@umich.edu
Requires-Python: >=3.10,<3.12
Classifier: Programming Language :: Python :: 3
Classifier: Programming Language :: Python :: 3.10
Classifier: Programming Language :: Python :: 3.11
Requires-Dist: umnet-napalm (>=0.3.0,<0.4.0)
